{
  "env": "development",
  "url": {
    "host": "localhost:3000",
    "prefix": "/",
    "ssl": false,
    "static": false
  },
  "store": {
    "adapter": "sqlite",
    "sqlite": {
      "location": "/tmp/jsbin.db"
    },
    "mysql": {
      "host": "localhost",
      "user": "root",
      "password": "",
      "database": "jsbin"
    }
  },
  "session": {
    "secret": "d41d8cd98f00b204e9800998ecf8427e"
  },
  "analytics": {
    "id": null
  },
  "smtp": {
    "service": "Gmail",
    "auth": {
        "user": "",
        "pass": ""
    }
  },
  "blacklist": {
    "html": ["processform.cgi", "habbo.com"],
    "css": [],
    "javascript": []
  }
}
